timeseries/__init__.py
timeseries/holder/InfluxDBHolder.py
timeseries/holder/__init__.py
timeseries/provider/InfluxDBProvider.py
timeseries/provider/__init__.py
timeseries/provider/point/PointBuilder.py
timeseries/provider/point/__init__.py
persuader_technology_automata_timeseries-0.0.6.dist-info/LICENSE
persuader_technology_automata_timeseries-0.0.6.dist-info/METADATA
persuader_technology_automata_timeseries-0.0.6.dist-info/WHEEL
persuader_technology_automata_timeseries-0.0.6.dist-info/top_level.txt
persuader_technology_automata_timeseries-0.0.6.dist-info/RECORD
