Metadata-Version: 2.1
Name: persuader-technology-automata-timeseries
Version: 0.0.6
Summary: Automata Time Series
Author: Persuader Technology
Author-email: software@persuader.technology
License: UNLICENSE
Classifier: Programming Language :: Python :: 3
License-File: LICENSE
Requires-Dist: influxdb-client (>=1.32.0)
Requires-Dist: persuader-technology-automata-core (>=0.6.0)
Requires-Dist: persuader-technology-automata-utilities (>=0.2.3)
Requires-Dist: persuader-technology-automata-logger (>=0.0.5)
